.gitignore
CHANGES.rst
README.rst
bdist_venv.py
setup.py
bdist_venv.egg-info/PKG-INFO
bdist_venv.egg-info/SOURCES.txt
bdist_venv.egg-info/dependency_links.txt
bdist_venv.egg-info/entry_points.txt
bdist_venv.egg-info/requires.txt
bdist_venv.egg-info/top_level.txt
bdist_venv.egg-info/zip-safe