Metadata-Version: 1.0
Name: bdist-venv
Version: 0.1.2
Summary: Python distutils extension to bundle package as a virtualenv.
Home-page: http://github.com/mgood/bdist_venv
Author: Matt Good
Author-email: matt@matt-good.net
License: BSD
Platform: any
Classifier: Intended Audience :: Developers
Classifier: License :: OSI Approved :: BSD License
Classifier: Operating System :: OS Independent
Classifier: Programming Language :: Python
Classifier: Topic :: Software Development :: Build Tools
Classifier: Topic :: Software Development :: Libraries :: Python Modules
